agentsjson/__init__.py
agentsjson/core/.DS_Store
agentsjson/core/__init__.py
agentsjson/core/executor.py
agentsjson/core/loader.py
agentsjson/core/models/__init__.py
agentsjson/core/models/__pycache__/__init__.cpython-313.pyc
agentsjson/core/models/__pycache__/auth.cpython-313.pyc
agentsjson/core/models/__pycache__/bundle.cpython-313.pyc
agentsjson/core/models/__pycache__/schema.cpython-313.pyc
agentsjson/core/models/__pycache__/tools.cpython-313.pyc
agentsjson/core/models/auth.py
agentsjson/core/models/bundle.py
agentsjson/core/models/schema.py
agentsjson/core/models/tools.py
agentsjson/core/parsetools.py
agentsjson/core/utils.py
agentsjson/integrations/__init__.py
agentsjson/integrations/giphy/__init__.py
agentsjson/integrations/giphy/giphy_client/__init__.py
agentsjson/integrations/giphy/giphy_client/__pycache__/__init__.cpython-313.pyc
agentsjson/integrations/giphy/giphy_client/__pycache__/api_client.cpython-313.pyc
agentsjson/integrations/giphy/giphy_client/__pycache__/configuration.cpython-313.pyc
agentsjson/integrations/giphy/giphy_client/__pycache__/rest.cpython-313.pyc
agentsjson/integrations/giphy/giphy_client/__pycache__/wrapper.cpython-313.pyc
agentsjson/integrations/giphy/giphy_client/api/__init__.py
agentsjson/integrations/giphy/giphy_client/api/__pycache__/__init__.cpython-313.pyc
agentsjson/integrations/giphy/giphy_client/api/__pycache__/default_api.cpython-313.pyc
agentsjson/integrations/giphy/giphy_client/api/default_api.py
agentsjson/integrations/giphy/giphy_client/api_client.py
agentsjson/integrations/giphy/giphy_client/configuration.py
agentsjson/integrations/giphy/giphy_client/models/__init__.py
agentsjson/integrations/giphy/giphy_client/models/__pycache__/__init__.cpython-313.pyc
agentsjson/integrations/giphy/giphy_client/models/__pycache__/all_of_emoji_response_data_items.cpython-313.pyc
agentsjson/integrations/giphy/giphy_client/models/__pycache__/all_ofinline_response2003_data_items.cpython-313.pyc
agentsjson-0.1.4.dist-info/LICENSE
agentsjson-0.1.4.dist-info/METADATA
agentsjson-0.1.4.dist-info/WHEEL
agentsjson-0.1.4.dist-info/RECORD
